LICENSE
MANIFEST.in
README.rst
setup.cfg
setup.py
docs/authors.rst
docs/autodoc.rst
docs/conf.py
docs/contributing.rst
docs/index.rst
docs/installation.rst
docs/readme.rst
docs/usage.rst
raw_tcp_connection/__init__.py
raw_tcp_connection/cli.py
raw_tcp_connection/raw_tcp_connection.py
raw_tcp_connection.egg-info/PKG-INFO
raw_tcp_connection.egg-info/SOURCES.txt
raw_tcp_connection.egg-info/dependency_links.txt
raw_tcp_connection.egg-info/entry_points.txt
raw_tcp_connection.egg-info/not-zip-safe
raw_tcp_connection.egg-info/requires.txt
raw_tcp_connection.egg-info/top_level.txt
tests/test_raw_tcp_connection.py